config/settings.yaml
src/__init__.py
src/ai/__init__.py
src/ai/base_provider.py
src/ai/local_provider.py
src/ai/prompts.py
src/cli/__init__.py
src/cli/config_command.py
src/cli/main.py
src/core/__init__.py
src/core/ai_processed_manager.py
src/core/library_logger.py
src/core/library_manager.py
src/core/metadata_fetcher.py
src/core/output_manager.py
src/core/transcript_fetcher.py
src/core/video_opener.py
src/utils/__init__.py
src/utils/config_loader.py
src/utils/formatter.py
src/utils/logger.py
src/utils/setup_wizard.py
src/utils/url_parser.py
src/utils/user_config.py
youtube_transcript_curator-1.0.0.dist-info/licenses/LICENSE
youtube_transcript_curator-1.0.0.dist-info/METADATA
youtube_transcript_curator-1.0.0.dist-info/WHEEL
youtube_transcript_curator-1.0.0.dist-info/entry_points.txt
youtube_transcript_curator-1.0.0.dist-info/top_level.txt
youtube_transcript_curator-1.0.0.dist-info/RECORD
