Metadata-Version: 2.4
Name: youtube-transcript-curator
Version: 1.0.0
Summary: Curate, organize, and explore YouTube transcripts with AI-powered analysis
Author-email: Marius Giurgi <marius.giurgi@gmail.com>
License: MIT License
Project-URL: Homepage, https://github.com/DolphinDream/youtube-transcript-curator
Project-URL: Documentation, https://github.com/DolphinDream/youtube-transcript-curator/blob/main/README.md
Project-URL: Repository, https://github.com/DolphinDream/youtube-transcript-curator
Project-URL: Issues, https://github.com/DolphinDream/youtube-transcript-curator/issues
Project-URL: Changelog, https://github.com/DolphinDream/youtube-transcript-curator/blob/main/CHANGELOG.md
Keywords: youtube,transcript,cli,curator,video,ai,claude
Classifier: Development Status :: 4 - Beta
Classifier: Environment :: Console
Classifier: Intended Audience :: Developers
Classifier: Intended Audience :: Education
Classifier: Intended Audience :: Science/Research
Classifier: Operating System :: MacOS
Classifier: Operating System :: POSIX :: Linux
Classifier: Operating System :: Microsoft :: Windows
Classifier: Programming Language :: Python :: 3
Classifier: Programming Language :: Python :: 3.10
Classifier: Programming Language :: Python :: 3.11
Classifier: Programming Language :: Python :: 3.12
Classifier: Programming Language :: Python :: 3.13
Classifier: Programming Language :: Python :: 3.14
Classifier: Topic :: Multimedia :: Video
Classifier: Topic :: Text Processing
Classifier: Topic :: Education
Classifier: Topic :: Scientific/Engineering :: Artificial Intelligence
Requires-Python: >=3.10
License-File: LICENSE
Requires-Dist: youtube-transcript-api>=1.2.3
Requires-Dist: yt-dlp>=2025.11.12
Requires-Dist: click>=8.1.7
Requires-Dist: PyYAML>=6.0.1
Requires-Dist: python-dotenv>=1.0.0
Requires-Dist: anthropic>=0.39.0
Provides-Extra: dev
Requires-Dist: pytest>=7.4.3; extra == "dev"
Requires-Dist: pytest-cov>=4.1.0; extra == "dev"
Requires-Dist: pytest-html>=4.1.1; extra == "dev"
Requires-Dist: pytest-mock>=3.12.0; extra == "dev"
Requires-Dist: pytest-xdist>=3.5.0; extra == "dev"
Requires-Dist: black>=23.12.1; extra == "dev"
Requires-Dist: pylint>=3.1.0; extra == "dev"
Requires-Dist: flake8>=6.1.0; extra == "dev"
Requires-Dist: isort>=5.13.2; extra == "dev"
Requires-Dist: ruff>=0.1.15; extra == "dev"
Requires-Dist: twine>=6.2.0; extra == "dev"
Requires-Dist: build>=1.0.0; extra == "dev"
Dynamic: license-file
